sensorkit/__init__.py
sensorkit/calibration.py
sensorkit/config.py
sensorkit/constants.py
sensorkit/controls.py
sensorkit/datastructures.py
sensorkit/detectors.py
sensorkit/devices.py
sensorkit/devicetree.py
sensorkit/meters.py
sensorkit/profiles.py
sensorkit/sensorkit.py
sensorkit/tools/mixins.py
sensorkit/virtuals/openmeteo.py
sensorkit/virtuals/static.py
sensorkit/virtuals/virtual.py
sensorkit-0.5.0.dist-info/LICENSE
sensorkit-0.5.0.dist-info/METADATA
sensorkit-0.5.0.dist-info/WHEEL
sensorkit-0.5.0.dist-info/RECORD
